Metadata-Version: 1.1
Name: namemysprint
Version: 1.0.0
Summary: Xzibit's favorite sprint-naming utility. (Not really.)
Home-page: https://github.com/dimaspivak/namemysprint
Author: Dima Spivak
Author-email: dima@spivak.ch
License: Apache Software License 2.0
Platform: UNKNOWN
Classifier: Development Status :: 3 - Alpha
Classifier: License :: OSI Approved :: Apache Software License
Classifier: Programming Language :: Python :: 3
Classifier: Programming Language :: Python :: 3.3
Classifier: Programming Language :: Python :: 3.4
Classifier: Programming Language :: Python :: 3.5
